web3_erc20_predefined/__init__.py
web3_erc20_predefined/core/__init__.py
web3_erc20_predefined/core/predefined_erc20.py
web3_erc20_predefined/core/predefined_erc20_constants.py
web3_erc20_predefined/predefined/__init__.py
web3_erc20_predefined/predefined/bsc/__init__.py
web3_erc20_predefined/predefined/bsc/busd.py
web3_erc20_predefined/predefined/bsc/wbnb.py
web3_erc20_predefined/predefined/bsc_testnet/__init__.py
web3_erc20_predefined/predefined/bsc_testnet/wbnb.py
web3_erc20_predefined/predefined/eth/__init__.py
web3_erc20_predefined/predefined/eth/dai.py
web3_erc20_predefined/predefined/eth/usdc.py
web3_erc20_predefined/predefined/eth/usdt.py
web3_erc20_predefined/predefined/eth/weth.py
web3_erc20_predefined-0.0.3.dist-info/LICENSE
web3_erc20_predefined-0.0.3.dist-info/METADATA
web3_erc20_predefined-0.0.3.dist-info/WHEEL
web3_erc20_predefined-0.0.3.dist-info/top_level.txt
web3_erc20_predefined-0.0.3.dist-info/RECORD
